torchlingo/__init__.py
torchlingo/config.py
torchlingo/inference.py
torchlingo/training.py
torchlingo/data_processing/__init__.py
torchlingo/data_processing/batching.py
torchlingo/data_processing/dataset.py
torchlingo/data_processing/vocab.py
torchlingo/models/__init__.py
torchlingo/models/lstm_simple.py
torchlingo/models/positional.py
torchlingo/models/transformer_simple.py
torchlingo/preprocessing/__init__.py
torchlingo/preprocessing/base.py
torchlingo/preprocessing/multilingual.py
torchlingo/preprocessing/sentencepiece.py
torchlingo-0.1.0.dist-info/licenses/LICENSE
torchlingo-0.1.0.dist-info/METADATA
torchlingo-0.1.0.dist-info/WHEEL
torchlingo-0.1.0.dist-info/top_level.txt
torchlingo-0.1.0.dist-info/RECORD
