Metadata-Version: 2.4
Name: torchlingo
Version: 0.1.0
Summary: Educational PyTorch NMT library for coursework and instruction.
Author: TorchLingo Maintainers
License-Expression: AGPL-3.0-or-later
Project-URL: Homepage, https://github.com/REPO_OWNER/torchlingo
Project-URL: Documentation, https://github.com/REPO_OWNER/torchlingo#readme
Project-URL: Repository, https://github.com/REPO_OWNER/torchlingo
Project-URL: Issues, https://github.com/REPO_OWNER/torchlingo/issues
Project-URL: Changelog, https://github.com/REPO_OWNER/torchlingo/releases
Keywords: nmt,neural-machine-translation,translation,pytorch,transformer,educational,deep-learning,nlp,natural-language-processing
Classifier: Development Status :: 4 - Beta
Classifier: Intended Audience :: Developers
Classifier: Intended Audience :: Education
Classifier: Intended Audience :: Science/Research
Classifier: Operating System :: OS Independent
Classifier: Programming Language :: Python :: 3
Classifier: Programming Language :: Python :: 3.10
Classifier: Programming Language :: Python :: 3.11
Classifier: Programming Language :: Python :: 3.12
Classifier: Topic :: Scientific/Engineering :: Artificial Intelligence
Classifier: Topic :: Text Processing :: Linguistic
Requires-Python: >=3.10
License-File: LICENSE
Requires-Dist: torch>=2.0
Requires-Dist: pandas>=1.5
Requires-Dist: sentencepiece>=0.1.99
Requires-Dist: tensorboard>=2.12
Requires-Dist: sacrebleu>=2.3
Provides-Extra: docs
Requires-Dist: mkdocs-material>=9.5; extra == "docs"
Requires-Dist: mkdocstrings[python]>=0.24; extra == "docs"
Requires-Dist: mkdocs-jupyter>=0.24; extra == "docs"
Requires-Dist: griffe>=0.40; extra == "docs"
Requires-Dist: ruff>=0.12; extra == "docs"
Requires-Dist: black>=24.0; extra == "docs"
Provides-Extra: dev
Requires-Dist: ruff>=0.1; extra == "dev"
Requires-Dist: isort>=5.12; extra == "dev"
Requires-Dist: build>=1.0; extra == "dev"
Requires-Dist: twine>=4.0; extra == "dev"
Dynamic: license-file
